{
  "$schema": "https://raw.githubusercontent.com/mavdaviddraughn/TaskSmithMCP/main/schema/scripts.json",
  "scripts": {
    "test-update-script-1756591605435": {
      "name": "test-update-script-1756591605435",
      "shell": "pwsh",
      "path": "C:\\Maverik\\TaskSmithMCP\\scripts/pwsh/test-update-script-1756591605435.ps1",
      "description": "Initial version",
      "tags": [],
      "ttlSeconds": null,
      "cwdStrategy": "repoRoot",
      "argsSchema": null,
      "createdAt": "2025-08-30T22:06:45.438Z",
      "updatedAt": "2025-08-30T22:06:45.438Z",
      "lastUsedAt": null,
      "createdBy": "system",
      "updatedBy": "system",
      "version": 1,
      "requireApproval": false,
      "changelog": []
    },
    "test-update-script-1756591764930": {
      "name": "test-update-script-1756591764930",
      "shell": "pwsh",
      "path": "C:\\Maverik\\TaskSmithMCP\\scripts/pwsh/test-update-script-1756591764930.ps1",
      "description": "Initial version",
      "tags": [],
      "ttlSeconds": null,
      "cwdStrategy": "repoRoot",
      "argsSchema": null,
      "createdAt": "2025-08-30T22:09:24.934Z",
      "updatedAt": "2025-08-30T22:09:24.934Z",
      "lastUsedAt": null,
      "createdBy": "system",
      "updatedBy": "system",
      "version": 1,
      "requireApproval": false,
      "changelog": []
    },
    "test-update-script-1756598840443": {
      "name": "test-update-script-1756598840443",
      "shell": "pwsh",
      "path": "C:\\Maverik\\TaskSmithMCP\\scripts/pwsh/test-update-script-1756598840443.ps1",
      "description": "Initial version",
      "tags": [],
      "ttlSeconds": null,
      "cwdStrategy": "repoRoot",
      "argsSchema": null,
      "createdAt": "2025-08-31T00:07:20.452Z",
      "updatedAt": "2025-08-31T00:07:20.452Z",
      "lastUsedAt": null,
      "createdBy": "system",
      "updatedBy": "system",
      "version": 1,
      "requireApproval": false,
      "changelog": [
        {
          "version": 1,
          "commit": "3c1317ea9597c79cb6881b8fc92527f79aaccdfe",
          "timestamp": "2025-08-31T00:07:20.452Z",
          "description": "Initial script creation",
          "tag": "mcp-scripts/test-update-script-1756598840443@1"
        }
      ]
    },
    "test-update-script-1756600175250": {
      "name": "test-update-script-1756600175250",
      "shell": "pwsh",
      "path": "C:\\Maverik\\TaskSmithMCP\\scripts/pwsh/test-update-script-1756600175250.ps1",
      "description": "Initial version",
      "tags": [],
      "ttlSeconds": null,
      "cwdStrategy": "repoRoot",
      "argsSchema": null,
      "createdAt": "2025-08-31T00:29:35.259Z",
      "updatedAt": "2025-08-31T00:29:35.259Z",
      "lastUsedAt": null,
      "createdBy": "system",
      "updatedBy": "system",
      "version": 1,
      "requireApproval": false,
      "changelog": [
        {
          "version": 1,
          "commit": "1075294cb2d71afeb6c6fc8085c900d7f68b3bbd",
          "timestamp": "2025-08-31T00:29:35.259Z",
          "description": "Initial script creation",
          "tag": "mcp-scripts/test-update-script-1756600175250@1"
        }
      ]
    },
    "test-script-2": {
      "name": "test-script-2",
      "shell": "bash",
      "path": "C:\\Maverik\\TaskSmithMCP\\scripts/bash/test-script-2.sh",
      "description": "Test bash script",
      "tags": [
        "test"
      ],
      "ttlSeconds": null,
      "cwdStrategy": "scriptDir",
      "argsSchema": null,
      "createdAt": "2025-08-31T00:30:38.764Z",
      "updatedAt": "2025-08-31T00:30:38.764Z",
      "lastUsedAt": null,
      "createdBy": "system",
      "updatedBy": "system",
      "version": 1,
      "requireApproval": false,
      "changelog": [
        {
          "version": 1,
          "commit": "3a803c4222c902d9861a5f2cbc9f4f18da6fa88d",
          "timestamp": "2025-08-31T00:30:38.764Z",
          "description": "Initial script creation",
          "tag": "mcp-scripts/test-script-2@1"
        }
      ]
    }
  }
}